README.md
jinja_macro_tags.py
setup.py
jinja_macro_tags.egg-info/PKG-INFO
jinja_macro_tags.egg-info/SOURCES.txt
jinja_macro_tags.egg-info/dependency_links.txt
jinja_macro_tags.egg-info/requires.txt
jinja_macro_tags.egg-info/top_level.txt