Metadata-Version: 1.0
Name: jinja-macro-tags
Version: 0.2
Summary: Macro loader and tag system to call macros
Home-page: http://github.com/frascoweb/jinja-macro-tags
Author: Maxime Bouroumeau-Fuseau
Author-email: maxime.bouroumeau@gmail.com
License: MIT
Platform: any
